<annotation>
	<folder>radar3000</folder>
	<filename>000154.jpg</filename>
	<path>D:\BaiduNetdiskDownload\radar3000\000154.jpg</path>
	<source>
		<database>Unknown</database>
	</source>
	<size>
		<width>0</width>
		<height>0</height>
		<depth>3</depth>
	</size>
	<segmented>0</segmented>
	<object>
		<name>B</name>
		<pose>Unspecified</pose>
		<truncated>0</truncated>
		<difficult>0</difficult>
		<bndbox>
			<xmin>307</xmin>
			<ymin>86</ymin>
			<xmax>325</xmax>
			<ymax>135</ymax>
		</bndbox>
	</object>
	<object>
		<name>B</name>
		<pose>Unspecified</pose>
		<truncated>0</truncated>
		<difficult>0</difficult>
		<bndbox>
			<xmin>326</xmin>
			<ymin>33</ymin>
			<xmax>335</xmax>
			<ymax>44</ymax>
		</bndbox>
	</object>
</annotation>
