<annotation>
	<folder>radar3000</folder>
	<filename>000206.jpg</filename>
	<path>D:\BaiduNetdiskDownload\radar3000\000206.jpg</path>
	<source>
		<database>Unknown</database>
	</source>
	<size>
		<width>0</width>
		<height>0</height>
		<depth>3</depth>
	</size>
	<segmented>0</segmented>
	<object>
		<name>B</name>
		<pose>Unspecified</pose>
		<truncated>0</truncated>
		<difficult>0</difficult>
		<bndbox>
			<xmin>222</xmin>
			<ymin>442</ymin>
			<xmax>235</xmax>
			<ymax>457</ymax>
		</bndbox>
	</object>
	<object>
		<name>B</name>
		<pose>Unspecified</pose>
		<truncated>0</truncated>
		<difficult>0</difficult>
		<bndbox>
			<xmin>267</xmin>
			<ymin>285</ymin>
			<xmax>289</xmax>
			<ymax>339</ymax>
		</bndbox>
	</object>
	<object>
		<name>B</name>
		<pose>Unspecified</pose>
		<truncated>0</truncated>
		<difficult>0</difficult>
		<bndbox>
			<xmin>302</xmin>
			<ymin>229</ymin>
			<xmax>325</xmax>
			<ymax>286</ymax>
		</bndbox>
	</object>
	<object>
		<name>B</name>
		<pose>Unspecified</pose>
		<truncated>0</truncated>
		<difficult>0</difficult>
		<bndbox>
			<xmin>308</xmin>
			<ymin>139</ymin>
			<xmax>322</xmax>
			<ymax>190</ymax>
		</bndbox>
	</object>
</annotation>
