<annotation>
	<folder>radar3000</folder>
	<filename>000436.jpg</filename>
	<path>D:\BaiduNetdiskDownload\radar3000\000436.jpg</path>
	<source>
		<database>Unknown</database>
	</source>
	<size>
		<width>0</width>
		<height>0</height>
		<depth>3</depth>
	</size>
	<segmented>0</segmented>
	<object>
		<name>B</name>
		<pose>Unspecified</pose>
		<truncated>0</truncated>
		<difficult>0</difficult>
		<bndbox>
			<xmin>520</xmin>
			<ymin>464</ymin>
			<xmax>543</xmax>
			<ymax>529</ymax>
		</bndbox>
	</object>
	<object>
		<name>B</name>
		<pose>Unspecified</pose>
		<truncated>0</truncated>
		<difficult>0</difficult>
		<bndbox>
			<xmin>321</xmin>
			<ymin>252</ymin>
			<xmax>357</xmax>
			<ymax>314</ymax>
		</bndbox>
	</object>
</annotation>
