<annotation>
	<folder>雷达标注</folder>
	<filename>001140.jpg</filename>
	<path>D:\雷达标注\001140.jpg</path>
	<source>
		<database>Unknown</database>
	</source>
	<size>
		<width>1024</width>
		<height>1024</height>
		<depth>3</depth>
	</size>
	<segmented>0</segmented>
	<object>
		<name>B</name>
		<pose>Unspecified</pose>
		<truncated>0</truncated>
		<difficult>0</difficult>
		<bndbox>
			<xmin>532</xmin>
			<ymin>507</ymin>
			<xmax>540</xmax>
			<ymax>534</ymax>
		</bndbox>
	</object>
	<object>
		<name>B</name>
		<pose>Unspecified</pose>
		<truncated>0</truncated>
		<difficult>0</difficult>
		<bndbox>
			<xmin>480</xmin>
			<ymin>294</ymin>
			<xmax>507</xmax>
			<ymax>320</ymax>
		</bndbox>
	</object>
	<object>
		<name>B</name>
		<pose>Unspecified</pose>
		<truncated>0</truncated>
		<difficult>0</difficult>
		<bndbox>
			<xmin>324</xmin>
			<ymin>306</ymin>
			<xmax>333</xmax>
			<ymax>338</ymax>
		</bndbox>
	</object>
	<object>
		<name>B</name>
		<pose>Unspecified</pose>
		<truncated>0</truncated>
		<difficult>0</difficult>
		<bndbox>
			<xmin>298</xmin>
			<ymin>272</ymin>
			<xmax>309</xmax>
			<ymax>292</ymax>
		</bndbox>
	</object>
	<object>
		<name>B</name>
		<pose>Unspecified</pose>
		<truncated>0</truncated>
		<difficult>0</difficult>
		<bndbox>
			<xmin>350</xmin>
			<ymin>108</ymin>
			<xmax>360</xmax>
			<ymax>126</ymax>
		</bndbox>
	</object>
</annotation>
