<annotation>
	<folder>leida</folder>
	<filename>002531.jpg</filename>
	<path>D:\Work\leida\002531.jpg</path>
	<source>
		<database>Unknown</database>
	</source>
	<size>
		<width>1024</width>
		<height>1024</height>
		<depth>3</depth>
	</size>
	<segmented>0</segmented>
	<object>
		<name>B</name>
		<pose>Unspecified</pose>
		<truncated>0</truncated>
		<difficult>0</difficult>
		<bndbox>
			<xmin>631</xmin>
			<ymin>670</ymin>
			<xmax>665</xmax>
			<ymax>682</ymax>
		</bndbox>
	</object>
	<object>
		<name>B</name>
		<pose>Unspecified</pose>
		<truncated>0</truncated>
		<difficult>0</difficult>
		<bndbox>
			<xmin>678</xmin>
			<ymin>667</ymin>
			<xmax>711</xmax>
			<ymax>681</ymax>
		</bndbox>
	</object>
	<object>
		<name>B</name>
		<pose>Unspecified</pose>
		<truncated>0</truncated>
		<difficult>0</difficult>
		<bndbox>
			<xmin>704</xmin>
			<ymin>695</ymin>
			<xmax>728</xmax>
			<ymax>715</ymax>
		</bndbox>
	</object>
	<object>
		<name>B</name>
		<pose>Unspecified</pose>
		<truncated>0</truncated>
		<difficult>0</difficult>
		<bndbox>
			<xmin>711</xmin>
			<ymin>701</ymin>
			<xmax>728</xmax>
			<ymax>726</ymax>
		</bndbox>
	</object>
	<object>
		<name>B</name>
		<pose>Unspecified</pose>
		<truncated>0</truncated>
		<difficult>0</difficult>
		<bndbox>
			<xmin>741</xmin>
			<ymin>634</ymin>
			<xmax>765</xmax>
			<ymax>652</ymax>
		</bndbox>
	</object>
	<object>
		<name>B</name>
		<pose>Unspecified</pose>
		<truncated>0</truncated>
		<difficult>0</difficult>
		<bndbox>
			<xmin>769</xmin>
			<ymin>630</ymin>
			<xmax>787</xmax>
			<ymax>652</ymax>
		</bndbox>
	</object>
	<object>
		<name>B</name>
		<pose>Unspecified</pose>
		<truncated>0</truncated>
		<difficult>0</difficult>
		<bndbox>
			<xmin>618</xmin>
			<ymin>815</ymin>
			<xmax>636</xmax>
			<ymax>846</ymax>
		</bndbox>
	</object>
	<object>
		<name>B</name>
		<pose>Unspecified</pose>
		<truncated>0</truncated>
		<difficult>0</difficult>
		<bndbox>
			<xmin>582</xmin>
			<ymin>830</ymin>
			<xmax>600</xmax>
			<ymax>867</ymax>
		</bndbox>
	</object>
	<object>
		<name>B</name>
		<pose>Unspecified</pose>
		<truncated>0</truncated>
		<difficult>0</difficult>
		<bndbox>
			<xmin>518</xmin>
			<ymin>800</ymin>
			<xmax>536</xmax>
			<ymax>823</ymax>
		</bndbox>
	</object>
	<object>
		<name>B</name>
		<pose>Unspecified</pose>
		<truncated>0</truncated>
		<difficult>0</difficult>
		<bndbox>
			<xmin>465</xmin>
			<ymin>593</ymin>
			<xmax>478</xmax>
			<ymax>619</ymax>
		</bndbox>
	</object>
	<object>
		<name>B</name>
		<pose>Unspecified</pose>
		<truncated>0</truncated>
		<difficult>0</difficult>
		<bndbox>
			<xmin>477</xmin>
			<ymin>595</ymin>
			<xmax>491</xmax>
			<ymax>625</ymax>
		</bndbox>
	</object>
	<object>
		<name>B</name>
		<pose>Unspecified</pose>
		<truncated>0</truncated>
		<difficult>0</difficult>
		<bndbox>
			<xmin>396</xmin>
			<ymin>679</ymin>
			<xmax>414</xmax>
			<ymax>693</ymax>
		</bndbox>
	</object>
</annotation>
